pyautd3_link_soem/__init__.py
pyautd3_link_soem/adapter.py
pyautd3_link_soem/core_id.py
pyautd3_link_soem/local.py
pyautd3_link_soem/py.typed
pyautd3_link_soem/remote.py
pyautd3_link_soem/status.py
pyautd3_link_soem/thread_priority.py
pyautd3_link_soem/bin/libautd3capi_link_soem.so
pyautd3_link_soem/native_methods/__init__.py
pyautd3_link_soem/native_methods/autd3_link_soem.py
pyautd3_link_soem/native_methods/autd3capi_link_soem.py
pyautd3_link_soem-35.0.1.dist-info/licenses/LICENSE
pyautd3_link_soem-35.0.1.dist-info/licenses/ThirdPartyNotice.txt
pyautd3_link_soem-35.0.1.dist-info/METADATA
pyautd3_link_soem-35.0.1.dist-info/WHEEL
pyautd3_link_soem-35.0.1.dist-info/top_level.txt
pyautd3_link_soem-35.0.1.dist-info/RECORD
