Metadata-Version: 2.4
Name: pyautd3_link_soem
Version: 35.0.1
Summary: autd3-link-soem library wrapper for python
Author-email: Shun Suzuki <suzuki@hapis.k.u-tokyo.ac.jp>
Project-URL: Repository, https://github.com/shinolab/pyautd3_link_soem.git
Classifier: Programming Language :: Python :: 3.11
Classifier: Programming Language :: Python :: 3.12
Classifier: Programming Language :: Python :: 3.13
Classifier: Operating System :: Microsoft :: Windows
Classifier: Operating System :: MacOS :: MacOS X
Classifier: Operating System :: POSIX
Requires-Python: >=3.11
License-File: LICENSE
License-File: ThirdPartyNotice.txt
Requires-Dist: numpy>=2
Requires-Dist: pyautd3==35.0.1
Dynamic: license-file
